af_process_image_renderer/__init__.py
af_process_image_renderer/api_client.py
af_process_image_renderer/configuration.py
af_process_image_renderer/rest.py
af_process_image_renderer/api/__init__.py
af_process_image_renderer/api/arista_flow_service_api.py
af_process_image_renderer/api/default_api.py
af_process_image_renderer/api/process_image_renderer_api.py
af_process_image_renderer/models/__init__.py
af_process_image_renderer/models/abort_service_exception.py
af_process_image_renderer/models/abort_transaction_exception.py
af_process_image_renderer/models/accessed_process_model_parameter.py
af_process_image_renderer/models/activity.py
af_process_image_renderer/models/activity_conf_extension.py
af_process_image_renderer/models/activity_configuration.py
af_process_image_renderer/models/af_configuration.py
af_process_image_renderer/models/agent_unknown_exception.py
af_process_image_renderer/models/authentication_exception.py
af_process_image_renderer/models/configuration_desc_entry.py
af_process_image_renderer/models/configuration_exception.py
af_process_image_renderer/models/data_consistency_exception.py
af_process_image_renderer/models/data_edge.py
af_process_image_renderer/models/data_element.py
af_process_image_renderer/models/data_source_exception.py
af_process_image_renderer/models/decision_activity.py
af_process_image_renderer/models/decision_statement.py
af_process_image_renderer/models/dummy_parent.py
af_process_image_renderer/models/ebp_instance_reference.py
af_process_image_renderer/models/edge.py
af_process_image_renderer/models/embedded_process.py
af_process_image_renderer/models/executable_business_process.py
af_process_image_renderer/models/execution_control_properties.py
af_process_image_renderer/models/ilm_exception.py
af_process_image_renderer/models/ilm_exception_cause.py
af_process_image_renderer/models/ilm_exception_stack_trace.py
af_process_image_renderer/models/ilm_exception_suppressed.py
af_process_image_renderer-3.0.3.dist-info/LICENSE
af_process_image_renderer-3.0.3.dist-info/METADATA
af_process_image_renderer-3.0.3.dist-info/WHEEL
af_process_image_renderer-3.0.3.dist-info/top_level.txt
af_process_image_renderer-3.0.3.dist-info/RECORD
